config/__init__.py
config/config_parser.py
config/database.py
config/index.py
config/logging.ini
models/__init__.py
models/analysiscollectionspectrumidentification.py
models/base.py
models/dbsequence.py
models/enzyme.py
models/index.py
models/match.py
models/modifiedpeptide.py
models/peptideevidence.py
models/projectdetail.py
models/projectsubdetail.py
models/searchmodification.py
models/spectradata.py
models/spectrum.py
models/spectrumidentificationprotocol.py
models/upload.py
parser/APIWriter.py
parser/DatabaseWriter.py
parser/MzIdParser.py
parser/SimpleFASTA.py
parser/Writer.py
parser/__init__.py
parser/__main__.py
parser/process_dataset.py
parser/schema_validate.py
parser/csv_parser/AbstractCsvParser.py
parser/csv_parser/FullCsvParser.py
parser/csv_parser/LinksOnlyCsvParser.py
parser/csv_parser/NoPeakListsCsvParser.py
parser/csv_parser/XiSpecCsvParser.py
parser/csv_parser/__init__.py
parser/database/__init__.py
parser/database/create_db_schema.py
parser/database/update_sqlite.py
parser/peaklistReader/PeakListWrapper.py
parser/peaklistReader/__init__.py
schema/__init__.py
schema/mzIdentML1.2.0.xsd
schema/mzIdentML1.3.0.xsd
tests/__init__.py
tests/compare.py
tests/db_pytest_fixtures.py
tests/parse_csv.py
tests/parse_mzid.py
tests/test_CsvParsers.py
tests/test_MzIdParser_ecoli_dsso.py
tests/test_MzIdParser_matrixscience.py
tests/test_MzIdParser_matrixscience2.py
tests/test_fasta_reader.py
tests/test_mzid_1_3_0.py
xi_mzidentml_converter-0.3.8.dist-info/licenses/LICENSE.md
xi_mzidentml_converter-0.3.8.dist-info/METADATA
xi_mzidentml_converter-0.3.8.dist-info/WHEEL
xi_mzidentml_converter-0.3.8.dist-info/entry_points.txt
xi_mzidentml_converter-0.3.8.dist-info/top_level.txt
xi_mzidentml_converter-0.3.8.dist-info/RECORD
